gfss_psft_scraper/__init__.py
gfss_psft_scraper-0.0.1.dist-info/METADATA
gfss_psft_scraper-0.0.1.dist-info/WHEEL
gfss_psft_scraper-0.0.1.dist-info/top_level.txt
gfss_psft_scraper-0.0.1.dist-info/RECORD
